
{
  "indexes": [
    {
      "collectionGroup": "users",
      "queryScope": "COLLECTION",
      "fields": [
        {
          "fieldPath": "email",
          "order": "ASCENDING"
        }
      ]
    },
    {
      "collectionGroup": "boards",
      "queryScope": "COLLECTION_GROUP",
      "fields": [
        {
          "fieldPath": "memberUids",
          "arrayConfig": "CONTAINS"
        }
      ]
    },
    {
      "collectionGroup": "teamRooms",
      "queryScope": "COLLECTION_GROUP",
      "fields": [
        {
          "fieldPath": "memberUids",
          "arrayConfig": "CONTAINS"
        }
      ]
    },
    {
      "collectionGroup": "workspaces",
      "queryScope": "COLLECTION",
      "fields": [
        {
          "fieldPath": "members.G65P8tzkuSYFAcZxcXde94QNdhq1",
          "order": "ASCENDING"
        }
      ]
    }
  ],
  "fieldOverrides": []
}
